camsniff-1.0.5.dist-info/licenses/LICENSE
python_core/__init__.py
python_core/ai_analyze.py
python_core/cli.py
python_core/config.py
python_core/cve_quick_search.py
python_core/logging_utils.py
python_core/web_backend.py
camsniff-1.0.5.dist-info/METADATA
camsniff-1.0.5.dist-info/WHEEL
camsniff-1.0.5.dist-info/entry_points.txt
camsniff-1.0.5.dist-info/top_level.txt
camsniff-1.0.5.dist-info/RECORD
