Metadata-Version: 2.4
Name: camsniff
Version: 1.0.5
Summary: IP camera reconnaissance toolkit: Python core + web backend
Author: CamSniff Authors
License: MIT
Project-URL: Homepage, https://github.com/John0n1/CamSniff
Project-URL: Issues, https://github.com/John0n1/CamSniff/issues
Keywords: camera,rtsp,iot,security,scanner,recon
Classifier: Programming Language :: Python :: 3
Classifier: Operating System :: POSIX :: Linux
Classifier: Environment :: Console
Classifier: Topic :: Security
Requires-Python: >=3.10
License-File: LICENSE
Requires-Dist: typer>=0.9.0
Requires-Dist: aiohttp>=3.9.0
Requires-Dist: fastapi>=0.117.0
Requires-Dist: uvicorn[standard]>=0.30.0
Provides-Extra: web
Requires-Dist: fastapi>=0.117.0; extra == "web"
Requires-Dist: uvicorn[standard]>=0.30.0; extra == "web"
Requires-Dist: flask>=3.1.0; extra == "web"
Requires-Dist: wsdiscovery>=2.0; extra == "web"
Provides-Extra: ai
Requires-Dist: opencv-python>=4.8; extra == "ai"
Provides-Extra: dev
Requires-Dist: pytest>=8.2; extra == "dev"
Requires-Dist: httpx>=0.28; extra == "dev"
Requires-Dist: black>=24.8; extra == "dev"
Requires-Dist: ruff>=0.6; extra == "dev"
Requires-Dist: pre-commit>=3.7; extra == "dev"
Dynamic: license-file
